<annotation><folder /><filename>img-00345.jpg</filename><path>img-00345.jpg</path><source><database>roboflow.ai</database></source><size><width>1280</width><height>720</height><depth>3</depth></size><segmented>0</segmented><object><name>ball</name><pose>Unspecified</pose><truncated>0</truncated><difficult>0</difficult><occluded>0</occluded><bndbox><xmin>422.2146301269531</xmin><xmax>72.38365173339844</xmax><ymin>517.5040283203125</ymin><ymax>83.64332580566406</ymax></bndbox></object></annotation>